dum_dum_irc-0.5.0.dist-info/licenses/LICENSE
dumdum/__init__.py
dumdum/appdirs.py
dumdum/logging.py
dumdum/client/__init__.py
dumdum/client/__main__.py
dumdum/client/app.py
dumdum/client/async_client.py
dumdum/client/chat_frame.py
dumdum/client/connect_frame.py
dumdum/client/errors.py
dumdum/client/event_thread.py
dumdum/client/file_entry.py
dumdum/client/scrollable_frame.py
dumdum/client/store.py
dumdum/client/styling.py
dumdum/db/__init__.py
dumdum/db/connection.py
dumdum/db/migrations.py
dumdum/db/scripts/client/0001-base.sql
dumdum/protocol/README.md
dumdum/protocol/__init__.py
dumdum/protocol/buffer.py
dumdum/protocol/channel.py
dumdum/protocol/constants.py
dumdum/protocol/enums.py
dumdum/protocol/errors.py
dumdum/protocol/interfaces.py
dumdum/protocol/message.py
dumdum/protocol/reader.py
dumdum/protocol/snowflake.py
dumdum/protocol/varchar.py
dumdum/protocol/client/__init__.py
dumdum/protocol/client/events.py
dumdum/protocol/client/messages.py
dumdum/protocol/client/protocol.py
dumdum/protocol/server/__init__.py
dumdum/protocol/server/events.py
dumdum/protocol/server/messages.py
dumdum/protocol/server/protocol.py
dumdum/server/__init__.py
dumdum/server/__main__.py
dumdum/server/connection.py
dumdum/server/manager.py
dumdum/server/state.py
dum_dum_irc-0.5.0.dist-info/METADATA
dum_dum_irc-0.5.0.dist-info/WHEEL
dum_dum_irc-0.5.0.dist-info/entry_points.txt
dum_dum_irc-0.5.0.dist-info/top_level.txt
dum_dum_irc-0.5.0.dist-info/RECORD
