Metadata-Version: 2.4
Name: dum-dum-irc
Version: 0.5.0
Summary: A non-standard internet relay chat program.
Author: thegamecracks
License: MIT
Project-URL: Homepage, https://github.com/thegamecracks/dum-dum-irc
Project-URL: Issue Tracker, https://github.com/thegamecracks/dum-dum-irc/issues
Requires-Python: >=3.11
License-File: LICENSE
Requires-Dist: importlib-resources>=6.1.3
Requires-Dist: platformdirs>=4.2.0
Provides-Extra: tests
Requires-Dist: coverage>=7.4.3; extra == "tests"
Requires-Dist: pytest>=8.0.2; extra == "tests"
Dynamic: license-file
